Metadata-Version: 1.0
Name: csv-from-root
Version: 1.0.1
Summary: From a given root directory will generate a csv file containing the files present in each subdir with respect to a given main_dir
Home-page: UNKNOWN
Author: Jack Geraghty
Author-email: jgeraghty049@gmail.com
License: UNKNOWN
Platform: UNKNOWN
